[
    {
        "nome": "Análise e Desenvolvimento de Sistemas-Lógica de Programação-P1",
        "professor": "Professor",
        "email_professor": "professor@docente.unip.org.br",
        "alunos": [
            "aluno1@unip.com",
            "rafael.costa@student.unip.com",
            "rodrigo.carvalho@student.unip.com"
        ]
    },
    {
        "nome": "Análise e Desenvolvimento de Sistemas-Matemática Discreta-P1",
        "professor": "Marcelo Silva",
        "email_professor": "marcelo.silva@docente.unip.org.br",
        "alunos": [
            "aluno1@unip.com",
            "rafael.costa@student.unip.com",
            "rodrigo.carvalho@student.unip.com"
        ]
    },
    {
        "nome": "Análise e Desenvolvimento de Sistemas-Banco de Dados-P2",
        "professor": "Professor",
        "email_professor": "professor@docente.unip.org.br",
        "alunos": [
            "paulo.ribeiro@student.unip.com",
            "fernando.araujo@student.unip.com"
        ]
    },
    {
        "nome": "Análise e Desenvolvimento de Sistemas-Programação Web-P2",
        "professor": "Ana Lima",
        "email_professor": "ana.lima@docente.unip.org.br",
        "alunos": [
            "paulo.ribeiro@student.unip.com",
            "fernando.araujo@student.unip.com"
        ]
    },
    {
        "nome": "Análise e Desenvolvimento de Sistemas-Engenharia de Software-P3",
        "professor": "Professor",
        "email_professor": "professor@docente.unip.org.br",
        "alunos": [
            "lucas.almeida@student.unip.com",
            "cecilia.marques@student.unip.com"
        ]
    },
    {
        "nome": "Análise e Desenvolvimento de Sistemas-Segurança da Informação-P4",
        "professor": "Professor",
        "email_professor": "professor@docente.unip.org.br",
        "alunos": [
            "mariana.silva@student.unip.com",
            "geraldo.barros@student.unip.com"
        ]
    },
    {
        "nome": "Ciência da Computação-Algoritmos e Estruturas de Dados-P1",
        "professor": "Ana Souza",
        "email_professor": "ana.souza@docente.unip.org.br",
        "alunos": []
    },
    {
        "nome": "Ciência da Computação-Introdução à Programação-P1",
        "professor": "Mariana Rocha",
        "email_professor": "mariana.rocha@docente.unip.org.br",
        "alunos": []
    },
    {
        "nome": "Ciência da Computação-Cálculo Diferencial-P2",
        "professor": "Bruno Mendes",
        "email_professor": "bruno.mendes@docente.unip.org.br",
        "alunos": [
            "patricia.souza@student.unip.com"
        ]
    },
    {
        "nome": "Ciência da Computação-Matemática Discreta-P2",
        "professor": "Lucas Pereira",
        "email_professor": "lucas.pereira@docente.unip.org.br",
        "alunos": [
            "patricia.souza@student.unip.com"
        ]
    },
    {
        "nome": "Ciência da Computação-Arquitetura de Computadores-P3",
        "professor": "Carla Rodrigues",
        "email_professor": "carla.rodrigues@docente.unip.org.br",
        "alunos": [
            "adriana.ribeiro@student.unip.com"
        ]
    },
    {
        "nome": "Ciência da Computação-Estruturas de Dados II-P3",
        "professor": "Roberto Santos",
        "email_professor": "roberto.santos@docente.unip.org.br",
        "alunos": [
            "adriana.ribeiro@student.unip.com"
        ]
    },
    {
        "nome": "Ciência da Computação-Sistemas Operacionais-P4",
        "professor": "Diego Alves",
        "email_professor": "diego.alves@docente.unip.org.br",
        "alunos": [
            "leticia.ramos@student.unip.com"
        ]
    },
    {
        "nome": "Ciência da Computação-Redes de Computadores-P5",
        "professor": "Eduarda Lima",
        "email_professor": "eduarda.lima@docente.unip.org.br",
        "alunos": [
            "marcos.oliveira@student.unip.com"
        ]
    },
    {
        "nome": "Ciência da Computação-Banco de Dados Avançado-P6",
        "professor": "Felipe Carvalho",
        "email_professor": "felipe.carvalho@docente.unip.org.br",
        "alunos": [
            "camila.rocha@student.unip.com"
        ]
    },
    {
        "nome": "Ciência da Computação-Inteligência Artificial-P7",
        "professor": "Gabriela Pereira",
        "email_professor": "gabriela.pereira@docente.unip.org.br",
        "alunos": [
            "monica.freitas@student.unip.com"
        ]
    },
    {
        "nome": "Ciência da Computação-Trabalho de Conclusão de Curso-P8",
        "professor": "Heitor Santos",
        "email_professor": "heitor.santos@docente.unip.org.br",
        "alunos": [
            "henrique.dias@student.unip.com"
        ]
    },
    {
        "nome": "Engenharia de Computação-Cálculo I-P1",
        "professor": "Irene Motta",
        "email_professor": "irene.motta@docente.unip.org.br",
        "alunos": [
            "andre.luiz@student.unip.com"
        ]
    },
    {
        "nome": "Engenharia de Computação-Física Geral-P2",
        "professor": "Joao Nunes",
        "email_professor": "joao.nunes@docente.unip.org.br",
        "alunos": [
            "gustavo.pereira@student.unip.com"
        ]
    },
    {
        "nome": "Engenharia de Computação-Circuitos Digitais-P3",
        "professor": "Karina Farias",
        "email_professor": "karina.farias@docente.unip.org.br",
        "alunos": [
            "otavio.sousa@student.unip.com"
        ]
    },
    {
        "nome": "Engenharia de Computação-Programação Estruturada-P4",
        "professor": "Leonardo Vieira",
        "email_professor": "leonardo.vieira@docente.unip.org.br",
        "alunos": []
    },
    {
        "nome": "Engenharia de Computação-Algoritmos e Análise-P4",
        "professor": "Paulo Carneiro",
        "email_professor": "paulo.carneiro@docente.unip.org.br",
        "alunos": []
    },
    {
        "nome": "Engenharia de Computação-Eletrônica Analógica-P5",
        "professor": "Mariana Torres",
        "email_professor": "mariana.torres@docente.unip.org.br",
        "alunos": [
            "fabio.lima@student.unip.com"
        ]
    },
    {
        "nome": "Engenharia de Computação-Sistemas Embarcados-P6",
        "professor": "Nicolas Rocha",
        "email_professor": "nicolas.rocha@docente.unip.org.br",
        "alunos": []
    },
    {
        "nome": "Engenharia de Computação-Controle e Automação-P7",
        "professor": "Olivia Martins",
        "email_professor": "olivia.martins@docente.unip.org.br",
        "alunos": [
            "beatriz.santos@student.unip.com"
        ]
    },
    {
        "nome": "Engenharia de Computação-Sistemas Operacionais-P8",
        "professor": "Pedro Costa",
        "email_professor": "pedro.costa@docente.unip.org.br",
        "alunos": []
    },
    {
        "nome": "Engenharia de Computação-Redes e Comunicações-P9",
        "professor": "Quintino Almeida",
        "email_professor": "quintino.almeida@docente.unip.org.br",
        "alunos": [
            "cesar.oliveira@student.unip.com"
        ]
    },
    {
        "nome": "Engenharia de Computação-Projeto de Engenharia-P10",
        "professor": "Renata Gomes",
        "email_professor": "renata.gomes@docente.unip.org.br",
        "alunos": [
            "helena.moreira@student.unip.com"
        ]
    },
    {
        "nome": "Sistemas de Informação-Análise de Sistemas-P1",
        "professor": "Silvia Moraes",
        "email_professor": "silvia.moraes@docente.unip.org.br",
        "alunos": [
            "vanessa.pinto@student.unip.com"
        ]
    },
    {
        "nome": "Sistemas de Informação-Banco de Dados-P2",
        "professor": "Tiago Martins",
        "email_professor": "tiago.martins@docente.unip.org.br",
        "alunos": [
            "elisa.duarte@student.unip.com"
        ]
    },
    {
        "nome": "Sistemas de Informação-Programação Web-P2",
        "professor": "Leticia Fonseca",
        "email_professor": "leticia.fonseca@docente.unip.org.br",
        "alunos": [
            "elisa.duarte@student.unip.com"
        ]
    },
    {
        "nome": "Sistemas de Informação-Engenharia de Software-P3",
        "professor": "Ursula Silva",
        "email_professor": "ursula.silva@docente.unip.org.br",
        "alunos": [
            "ricardo.lopes@student.unip.com"
        ]
    },
    {
        "nome": "Sistemas de Informação-Redes de Computadores-P4",
        "professor": "Vitor Souza",
        "email_professor": "vitor.souza@docente.unip.org.br",
        "alunos": [
            "bruna.fernandes@student.unip.com"
        ]
    },
    {
        "nome": "Sistemas de Informação-Gestão de Projetos-P5",
        "professor": "Walter Lima",
        "email_professor": "walter.lima@docente.unip.org.br",
        "alunos": []
    },
    {
        "nome": "Sistemas de Informação-Segurança da Informação-P6",
        "professor": "Xenia Pereira",
        "email_professor": "xenia.pereira@docente.unip.org.br",
        "alunos": [
            "priscila.santos@student.unip.com"
        ]
    },
    {
        "nome": "Sistemas de Informação-Business Intelligence-P7",
        "professor": "Yasmin Carneiro",
        "email_professor": "yasmin.carneiro@docente.unip.org.br",
        "alunos": [
            "igor.ramos@student.unip.com"
        ]
    },
    {
        "nome": "Sistemas de Informação-Trabalho de Conclusão de Curso-P8",
        "professor": "Ze Rodrigues",
        "email_professor": "ze.rodrigues@docente.unip.org.br",
        "alunos": [
            "sara.lopes@student.unip.com"
        ]
    },
    {
        "nome": "Redes de Computadores (Tecnólogo)-Fundamentos de Redes-P1",
        "professor": "Amanda Luiz",
        "email_professor": "amanda.luiz@docente.unip.org.br",
        "alunos": [
            "thiago.gomes@student.unip.com"
        ]
    },
    {
        "nome": "Redes de Computadores (Tecnólogo)-Topologias e Meios de Transmissão-P1",
        "professor": "Fabiana Mello",
        "email_professor": "fabiana.mello@docente.unip.org.br",
        "alunos": [
            "thiago.gomes@student.unip.com"
        ]
    },
    {
        "nome": "Redes de Computadores (Tecnólogo)-Interconexão de Redes-P2",
        "professor": "Bruno Leite",
        "email_professor": "bruno.leite@docente.unip.org.br",
        "alunos": [
            "fernanda.castro@student.unip.com",
            "hugo.santana@student.unip.com"
        ]
    },
    {
        "nome": "Redes de Computadores (Tecnólogo)-Segurança de Redes-P3",
        "professor": "Camila Santos",
        "email_professor": "camila.santos@docente.unip.org.br",
        "alunos": [
            "rosa.carvalho@student.unip.com"
        ]
    },
    {
        "nome": "Redes de Computadores (Tecnólogo)-Administração de Redes-P4",
        "professor": "Diego Pinto",
        "email_professor": "diego.pinto@docente.unip.org.br",
        "alunos": [
            "lucas.mendes@student.unip.com",
            "renan.bittencourt@student.unip.com"
        ]
    },
    {
        "nome": "Segurança da Informação-Criptografia-P1",
        "professor": "Eloisa Fernandes",
        "email_professor": "eloisa.fernandes@docente.unip.org.br",
        "alunos": [
            "sabrina.rocha@student.unip.com"
        ]
    },
    {
        "nome": "Segurança da Informação-Segurança em Redes-P2",
        "professor": "Fabio Goncalves",
        "email_professor": "fabio.goncalves@docente.unip.org.br",
        "alunos": []
    },
    {
        "nome": "Segurança da Informação-Gestão de Segurança da Informação-P3",
        "professor": "Gisele Amaral",
        "email_professor": "gisele.amaral@docente.unip.org.br",
        "alunos": []
    },
    {
        "nome": "Segurança da Informação-Criptografia Aplicada-P3",
        "professor": "Henrique Souza",
        "email_professor": "henrique.souza@docente.unip.org.br",
        "alunos": []
    },
    {
        "nome": "Segurança da Informação-Análise de Riscos-P4",
        "professor": "Hugo Barros",
        "email_professor": "hugo.barros@docente.unip.org.br",
        "alunos": [
            "vladimir.teixeira@student.unip.com"
        ]
    },
    {
        "nome": "Segurança da Informação-Forense Computacional-P5",
        "professor": "Isabela Castro",
        "email_professor": "isabela.castro@docente.unip.org.br",
        "alunos": [
            "paula.nunes@student.unip.com"
        ]
    },
    {
        "nome": "Segurança da Informação-Políticas e Compliance-P6",
        "professor": "Joana Felix",
        "email_professor": "joana.felix@docente.unip.org.br",
        "alunos": [
            "daniel.alves@student.unip.com"
        ]
    },
    {
        "nome": "Segurança da Informação-Segurança de Aplicações-P7",
        "professor": "Kleber Rodrigues",
        "email_professor": "kleber.rodrigues@docente.unip.org.br",
        "alunos": [
            "marcia.pires@student.unip.com"
        ]
    },
    {
        "nome": "Segurança da Informação-Trabalho de Conclusão de Curso-P8",
        "professor": "Lucia Pereira",
        "email_professor": "lucia.pereira@docente.unip.org.br",
        "alunos": [
            "clara.nascimento@student.unip.com"
        ]
    },
    {
        "nome": "Inteligência Artificial (Tecnólogo)-Introdução à IA-P1",
        "professor": "Mateus Almeida",
        "email_professor": "mateus.almeida@docente.unip.org.br",
        "alunos": [
            "alice.martins@student.unip.com"
        ]
    },
    {
        "nome": "Inteligência Artificial (Tecnólogo)-Aprendizado de Máquina-P2",
        "professor": "Natasha Oliveira",
        "email_professor": "natasha.oliveira@docente.unip.org.br",
        "alunos": [
            "beatriz.moraes@student.unip.com",
            "yuri.marques@student.unip.com"
        ]
    },
    {
        "nome": "Inteligência Artificial (Tecnólogo)-Processamento de Linguagem Natural-P3",
        "professor": "Otavio Sousa",
        "email_professor": "otavio.sousa@docente.unip.org.br",
        "alunos": [
            "eduardo.castro@student.unip.com",
            "igor.fernandes@student.unip.com"
        ]
    },
    {
        "nome": "Inteligência Artificial (Tecnólogo)-Projeto de IA-P4",
        "professor": "Patricia Mendes",
        "email_professor": "patricia.mendes@docente.unip.org.br",
        "alunos": [
            "matheus.vieira@student.unip.com"
        ]
    },
    {
        "nome": "Ciência de Dados-Estatística-P1",
        "professor": "Rafaela Vieira",
        "email_professor": "rafaela.vieira@docente.unip.org.br",
        "alunos": [
            "isadora.gomes@student.unip.com"
        ]
    },
    {
        "nome": "Ciência de Dados-Probabilidade-P2",
        "professor": "Samuel Cunha",
        "email_professor": "samuel.cunha@docente.unip.org.br",
        "alunos": [
            "lara.barbosa@student.unip.com"
        ]
    },
    {
        "nome": "Ciência de Dados-Programação para Data Science-P3",
        "professor": "Tatiana Lopes",
        "email_professor": "tatiana.lopes@docente.unip.org.br",
        "alunos": [
            "suelen.ribeiro@student.unip.com"
        ]
    },
    {
        "nome": "Ciência de Dados-Banco de Dados para Data Science-P4",
        "professor": "Ugo Machado",
        "email_professor": "ugo.machado@docente.unip.org.br",
        "alunos": [
            "victor.nunes@student.unip.com"
        ]
    },
    {
        "nome": "Ciência de Dados-Machine Learning-P5",
        "professor": "Valentina Silveira",
        "email_professor": "valentina.silveira@docente.unip.org.br",
        "alunos": [
            "bianca.costa@student.unip.com"
        ]
    },
    {
        "nome": "Ciência de Dados-Projeto de Data Science-P6",
        "professor": "William Nascimento",
        "email_professor": "william.nascimento@docente.unip.org.br",
        "alunos": [
            "marcos.dias@student.unip.com"
        ]
    },
    {
        "nome": "Engenharia de Software-Modelagem UML-P1",
        "professor": "Xavier Silva",
        "email_professor": "xavier.silva@docente.unip.org.br",
        "alunos": []
    },
    {
        "nome": "Engenharia de Software-Processos de Software-P2",
        "professor": "Yago Cardoso",
        "email_professor": "yago.cardoso@docente.unip.org.br",
        "alunos": [
            "sofia.almeida@student.unip.com",
            "vitor.hugo@student.unip.com"
        ]
    },
    {
        "nome": "Engenharia de Software-Arquitetura de Software-P3",
        "professor": "Zuleica Pinto",
        "email_professor": "zuleica.pinto@docente.unip.org.br",
        "alunos": [
            "daniela.almeida@student.unip.com"
        ]
    },
    {
        "nome": "Engenharia de Software-Testes de Software-P4",
        "professor": "Analu Freitas",
        "email_professor": "analu.freitas@docente.unip.org.br",
        "alunos": []
    },
    {
        "nome": "Engenharia de Software-Manutenção de Software-P5",
        "professor": "Bruno Costa",
        "email_professor": "bruno.costa@docente.unip.org.br",
        "alunos": [
            "guilherme.pinto@student.unip.com"
        ]
    },
    {
        "nome": "Engenharia de Software-DevOps-P6",
        "professor": "Carolina Monteiro",
        "email_professor": "carolina.monteiro@docente.unip.org.br",
        "alunos": []
    },
    {
        "nome": "Engenharia de Software-Integração Contínua-P6",
        "professor": "Diego Silva",
        "email_professor": "diego.silva@docente.unip.org.br",
        "alunos": []
    },
    {
        "nome": "Engenharia de Software-Gestão de Requisitos-P7",
        "professor": "Danilo Siqueira",
        "email_professor": "danilo.siqueira@docente.unip.org.br",
        "alunos": [
            "ramon.pinto@student.unip.com"
        ]
    },
    {
        "nome": "Engenharia de Software-Trabalho de Conclusão de Curso-P8",
        "professor": "Elaine Moreira",
        "email_professor": "elaine.moreira@docente.unip.org.br",
        "alunos": [
            "nicole.fernandes@student.unip.com"
        ]
    }
]